aspcol/__init__.py
aspcol/distance.py
aspcol/planewaves.py
aspcol/plot.py
aspcol/spatialcovarianceestimation.py
aspcol/sphericalharmonics.py
aspcol/sphericalharmonics_jax.py
aspcol/utilities.py
aspcol/kernelinterpolation/__init__.py
aspcol/kernelinterpolation/kernel.py
aspcol/kernelinterpolation/single_frequency_kernels.py
aspcol/kernelinterpolation_jax/__init__.py
aspcol/kernelinterpolation_jax/kernel_jax.py
aspcol/soundfieldcontrol/__init__.py
aspcol/soundfieldcontrol/sound_field_control.py
aspcol/soundfieldcontrol/sound_zone_control.py
aspcol/soundfieldcontrol/sound_zone_control_sinr.py
aspcol/soundfieldcontrol/spatial_audio.py
aspcol/soundfieldestimation/__init__.py
aspcol/soundfieldestimation/kernel_estimation.py
aspcol/soundfieldestimation/moving_microphone.py
aspcol/soundfieldestimation/sound_field_estimation.py
aspcol/soundfieldestimation/spherical_harmonics_estimation.py
aspcol/soundfieldestimation_jax/__init__.py
aspcol/soundfieldestimation_jax/kernel_estimation_jax.py
aspcol/soundfieldestimation_jax/moving_microphone_jax.py
aspcol-0.0.2.dist-info/licenses/LICENSE
aspcol-0.0.2.dist-info/METADATA
aspcol-0.0.2.dist-info/WHEEL
aspcol-0.0.2.dist-info/top_level.txt
aspcol-0.0.2.dist-info/RECORD
