Metadata-Version: 2.4
Name: aspcol
Version: 0.0.2
Author-email: Jesper Brunnström <jesper_brunnstrom@hotmail.com>
Project-URL: Documentation, https://sounds-research.github.io/aspcol/
Project-URL: Repository, https://github.com/SOUNDS-RESEARCH/aspcol
Classifier: Operating System :: OS Independent
Classifier: Programming Language :: Python :: 3
Classifier: License :: OSI Approved :: MIT License
Requires-Python: >=3.11
License-File: LICENSE
Requires-Dist: numpy
Requires-Dist: scipy
Requires-Dist: aspcore
Requires-Dist: numba
Requires-Dist: wigners
Requires-Dist: jax
Requires-Dist: matplotlib
Provides-Extra: test
Requires-Dist: pytest; extra == "test"
Requires-Dist: hypothesis; extra == "test"
Requires-Dist: cvxpy; extra == "test"
Requires-Dist: aspsim; extra == "test"
Provides-Extra: examples
Requires-Dist: aspsim; extra == "examples"
Dynamic: license-file
